flake8_libfaketime.py
flake8_libfaketime-1.1.dist-info/DESCRIPTION.rst
flake8_libfaketime-1.1.dist-info/METADATA
flake8_libfaketime-1.1.dist-info/RECORD
flake8_libfaketime-1.1.dist-info/WHEEL
flake8_libfaketime-1.1.dist-info/entry_points.txt
flake8_libfaketime-1.1.dist-info/metadata.json
flake8_libfaketime-1.1.dist-info/top_level.txt
